metis/__init__.py
metis/readwrite.py
metis_utils-0.0.2.dist-info/LICENSE
metis_utils-0.0.2.dist-info/METADATA
metis_utils-0.0.2.dist-info/WHEEL
metis_utils-0.0.2.dist-info/top_level.txt
metis_utils-0.0.2.dist-info/RECORD
