Metadata-Version: 2.1
Name: metis-utils
Version: 0.0.2
Summary: A collection of utilities for faster data science project development.
Home-page: https://github.com/thisismetis/metis-utils
Author: Cliff Clive
Author-email: cliff.clive@thisismetis.com
License: UNKNOWN
Platform: UNKNOWN
Classifier: Programming Language :: Python :: 3
Classifier: License :: OSI Approved :: MIT License
Classifier: Operating System :: OS Independent
